IfcLCA/__init__.py
IfcLCA/analysis.py
IfcLCA/db_reader.py
IfcLCA/lca.py
IfcLCA/optioneering.py
IfcLCA/reporter.py
IfcLCA/utils/__init__.py
IfcLCA/utils/selector.py
ifclca-0.1.0a2.dist-info/licenses/LICENSE
tests/__init__.py
tests/test_analysis.py
tests/test_db_reader.py
tests/test_integration.py
tests/test_lca.py
tests/test_optioneering.py
tests/test_reporter.py
tests/test_selector.py
ifclca-0.1.0a2.dist-info/METADATA
ifclca-0.1.0a2.dist-info/WHEEL
ifclca-0.1.0a2.dist-info/top_level.txt
ifclca-0.1.0a2.dist-info/RECORD
